{"assets/images/.DS_Store":["assets/images/.DS_Store"],"assets/images/Checken Burger.png":["assets/images/Checken Burger.png"],"assets/images/bag.png":["assets/images/bag.png"],"assets/images/burger.png":["assets/images/burger.png"],"assets/images/chicken.png":["assets/images/chicken.png"],"assets/images/circle.png":["assets/images/circle.png"],"assets/images/facebook.png":["assets/images/facebook.png"],"assets/images/google.png":["assets/images/google.png"],"assets/images/logo.png":["assets/images/logo.png"],"assets/images/onboarding.png":["assets/images/onboarding.png"],"assets/images/pfp.png":["assets/images/pfp.png"],"assets/images/pizza.png":["assets/images/pizza.png"],"assets/images/twitter.png":["assets/images/twitter.png"],"assets/images/vegitables.png":["assets/images/vegitables.png"],"assets/images/zingerBurger.png":["assets/images/zingerBurger.png"],"packages/cupertino_icons/assets/CupertinoIcons.ttf":["packages/cupertino_icons/assets/CupertinoIcons.ttf"]}